iperturb/__init__.py
iperturb/model.py
iperturb/preprocess.py
iperturb/utils.py
iperturb-0.2.9.dist-info/METADATA
iperturb-0.2.9.dist-info/WHEEL
iperturb-0.2.9.dist-info/top_level.txt
iperturb-0.2.9.dist-info/RECORD
