Metadata-Version: 2.1
Name: iperturb
Version: 0.2.9
Summary: Atlas-level data integration in multi-condition single-cell genomics
Home-page: https://github.com/BillyChen123/iPerturb
Author: Billy Chen
Author-email: cyz2022@stu.xjtu.edu.cn
Classifier: Programming Language :: Python :: 3
Classifier: License :: OSI Approved :: MIT License
Classifier: Operating System :: OS Independent
Requires-Python: >=3.6
Requires-Dist: anndata (>=0.7.4)
Requires-Dist: numpy (>=1.18.5)
Requires-Dist: pandas (>=1.1.1)
Requires-Dist: pyro-ppl
Requires-Dist: scanpy (>=1.6.0)
Requires-Dist: scikit-learn
Requires-Dist: scipy
Requires-Dist: setuptools
Requires-Dist: torch
Requires-Dist: scikit-misc
